PITONSHIKI/__init__.py
PITONSHIKI/pract1.py
PITONSHIKI/pract2.py
PITONSHIKI/pract3.py
PITONSHIKI/pract4.py
PITONSHIKI/pract5.py
PITONSHIKI/pract6.py
PITONSHIKI/pract7_8.py
PITONSHIKI-0.0.dist-info/METADATA
PITONSHIKI-0.0.dist-info/WHEEL
PITONSHIKI-0.0.dist-info/top_level.txt
PITONSHIKI-0.0.dist-info/RECORD
