Metadata-Version: 2.1
Name: PITONSHIKI
Version: 0.0
Summary: AnyModulesToAnalize
Home-page: https://github.com/PITONSHIKI/PITONSHIKI
Author: pitonshiki
Author-email: GlebinskiGleb@yandex.ru
License: MIT
Platform: UNKNOWN
